easy_ai_module/__init__.py
easy_ai_module/gemini_client.py
easy_ai_module/model_guide.py
easy_ai_module-0.1.2.dist-info/licenses/LICENSE
easy_ai_module-0.1.2.dist-info/METADATA
easy_ai_module-0.1.2.dist-info/WHEEL
easy_ai_module-0.1.2.dist-info/top_level.txt
easy_ai_module-0.1.2.dist-info/RECORD
